StatsTestDrugPatients/__init__.py
stats_drug_test_patients-1.0.1.dist-info/METADATA
stats_drug_test_patients-1.0.1.dist-info/WHEEL
stats_drug_test_patients-1.0.1.dist-info/top_level.txt
stats_drug_test_patients-1.0.1.dist-info/RECORD
